iipv/__init__.py
iipv/iipv.py
iipv/image_preloader.py
iipv/transforms.py
iipv/viewer.py
iipv-0.0.1.dist-info/LICENSE
iipv-0.0.1.dist-info/METADATA
iipv-0.0.1.dist-info/WHEEL
iipv-0.0.1.dist-info/entry_points.txt
iipv-0.0.1.dist-info/top_level.txt
iipv-0.0.1.dist-info/RECORD
