Metadata-Version: 2.1
Name: iipv
Version: 0.0.1
Summary: Integrate image sequence visualization into your Python project
Author: Axel Davy
Maintainer: Axel Davy
License: MIT License
Project-URL: Repository, https://github.com/axeldavy/IntegratedImageProcessingViewer
Classifier: Development Status :: 2 - Pre-Alpha
Classifier: Intended Audience :: Education
Classifier: Intended Audience :: Developers
Classifier: Intended Audience :: Science/Research
Classifier: License :: OSI Approved :: MIT License
Classifier: Operating System :: MacOS
Classifier: Operating System :: Microsoft :: Windows :: Windows 10
Classifier: Operating System :: POSIX
Classifier: Operating System :: Unix
Classifier: Programming Language :: Cython
Classifier: Programming Language :: Python :: 3
Classifier: Topic :: Software Development :: User Interfaces
Classifier: Topic :: Software Development :: Libraries :: Python Modules
License-File: LICENSE
Requires-Dist: dearcygui
Requires-Dist: imageio
Requires-Dist: numpy
Provides-Extra: lycon
Requires-Dist: lycon; extra == "lycon"
Provides-Extra: tiff
Requires-Dist: tifffile; extra == "tiff"
